pyproject.toml
setup.py
thinkdata/__init__.py
thinkdata/chart.py
thinkdata/metric_system.py
thinkdata.egg-info/PKG-INFO
thinkdata.egg-info/SOURCES.txt
thinkdata.egg-info/dependency_links.txt
thinkdata.egg-info/requires.txt
thinkdata.egg-info/top_level.txt