Metadata-Version: 1.0
Name: thinkdata
Version: 0.1.1
Summary: Data analysis tool for Metric System
Home-page: UNKNOWN
Author: brendon.lin
Author-email: brendon.lin@outlook.com
License: UNKNOWN
Platform: UNKNOWN
